[
  {
    "sourceText": "grasp",
    "text": "grasp",
    "level": "1",
    "translation": "つかむ / 理解する",
    "exampleJa": "",
    "exampleEn": "It took me a while to grasp the main idea.",
    "status": "ready",
    "issues": "",
    "notes": "curated_batch24"
  },
  {
    "sourceText": "summon",
    "text": "summon",
    "level": "1",
    "translation": "呼び出す / 呼び寄せる",
    "exampleJa": "",
    "exampleEn": "The manager summoned everyone to the meeting room.",
    "status": "ready",
    "issues": "",
    "notes": "curated_batch24"
  },
  {
    "sourceText": "expel",
    "text": "expel",
    "level": "1",
    "translation": "追放する / 除名する",
    "exampleJa": "",
    "exampleEn": "The school decided to expel the student for repeated misconduct.",
    "status": "ready",
    "issues": "",
    "notes": "curated_batch24"
  },
  {
    "sourceText": "redeem",
    "text": "redeem",
    "level": "1",
    "translation": "償う / 引き換える",
    "exampleJa": "",
    "exampleEn": "Customers can redeem the coupon online.",
    "status": "ready",
    "issues": "",
    "notes": "curated_batch24"
  },
  {
    "sourceText": "comprise",
    "text": "comprise",
    "level": "1",
    "translation": "成る / 含む",
    "exampleJa": "",
    "exampleEn": "The committee comprises five members.",
    "status": "ready",
    "issues": "",
    "notes": "curated_batch24"
  },
  {
    "sourceText": "prevail",
    "text": "prevail",
    "level": "1",
    "translation": "広まる / 打ち勝つ",
    "exampleJa": "",
    "exampleEn": "A calm atmosphere prevailed throughout the event.",
    "status": "ready",
    "issues": "",
    "notes": "curated_batch24"
  },
  {
    "sourceText": "eject",
    "text": "eject",
    "level": "1",
    "translation": "追い出す / 射出する",
    "exampleJa": "",
    "exampleEn": "Security officers ejected the man from the stadium.",
    "status": "ready",
    "issues": "",
    "notes": "curated_batch24"
  },
  {
    "sourceText": "falsify",
    "text": "falsify",
    "level": "1",
    "translation": "改ざんする / 偽る",
    "exampleJa": "",
    "exampleEn": "It is illegal to falsify official records.",
    "status": "ready",
    "issues": "",
    "notes": "curated_batch24"
  },
  {
    "sourceText": "obstruct",
    "text": "obstruct",
    "level": "1",
    "translation": "妨げる / ふさぐ",
    "exampleJa": "",
    "exampleEn": "A fallen tree obstructed the road.",
    "status": "ready",
    "issues": "",
    "notes": "curated_batch24"
  },
  {
    "sourceText": "depict",
    "text": "depict",
    "level": "1",
    "translation": "描写する",
    "exampleJa": "",
    "exampleEn": "The painting depicts life in the countryside.",
    "status": "ready",
    "issues": "",
    "notes": "curated_batch24"
  },
  {
    "sourceText": "tremble",
    "text": "tremble",
    "level": "1",
    "translation": "震える",
    "exampleJa": "",
    "exampleEn": "Her hands began to tremble from the cold.",
    "status": "ready",
    "issues": "",
    "notes": "curated_batch24"
  },
  {
    "sourceText": "confess",
    "text": "confess",
    "level": "1",
    "translation": "告白する / 自白する",
    "exampleJa": "",
    "exampleEn": "He finally confessed that he had made the mistake.",
    "status": "ready",
    "issues": "",
    "notes": "curated_batch24"
  },
  {
    "sourceText": "ache",
    "text": "ache",
    "level": "1",
    "translation": "痛む / 痛み",
    "exampleJa": "",
    "exampleEn": "My shoulders ached after the long drive.",
    "status": "ready",
    "issues": "",
    "notes": "curated_batch24"
  },
  {
    "sourceText": "assert",
    "text": "assert",
    "level": "1",
    "translation": "主張する",
    "exampleJa": "",
    "exampleEn": "She asserted that the data were accurate.",
    "status": "ready",
    "issues": "",
    "notes": "curated_batch24"
  },
  {
    "sourceText": "contemplate",
    "text": "contemplate",
    "level": "1",
    "translation": "熟考する / じっと見つめる",
    "exampleJa": "",
    "exampleEn": "They are contemplating a move to another city.",
    "status": "ready",
    "issues": "",
    "notes": "curated_batch24"
  },
  {
    "sourceText": "delegate",
    "text": "delegate",
    "level": "1",
    "translation": "委任する / 代表者",
    "exampleJa": "",
    "exampleEn": "A good leader knows how to delegate tasks.",
    "status": "ready",
    "issues": "",
    "notes": "curated_batch24"
  },
  {
    "sourceText": "propel",
    "text": "propel",
    "level": "1",
    "translation": "推進する / 駆り立てる",
    "exampleJa": "",
    "exampleEn": "Strong winds propelled the boat forward.",
    "status": "ready",
    "issues": "",
    "notes": "curated_batch24"
  },
  {
    "sourceText": "recede",
    "text": "recede",
    "level": "1",
    "translation": "後退する / 薄れる",
    "exampleJa": "",
    "exampleEn": "The floodwaters began to recede by morning.",
    "status": "ready",
    "issues": "",
    "notes": "curated_batch24"
  },
  {
    "sourceText": "scrape",
    "text": "scrape",
    "level": "1",
    "translation": "こする / こすり取る",
    "exampleJa": "",
    "exampleEn": "He scraped the mud off his shoes.",
    "status": "ready",
    "issues": "",
    "notes": "curated_batch24"
  },
  {
    "sourceText": "smash",
    "text": "smash",
    "level": "1",
    "translation": "粉々に壊す / 激突する",
    "exampleJa": "",
    "exampleEn": "The ball smashed a window.",
    "status": "ready",
    "issues": "",
    "notes": "curated_batch24"
  },
  {
    "sourceText": "scold",
    "text": "scold",
    "level": "1",
    "translation": "しかる",
    "exampleJa": "",
    "exampleEn": "She scolded him for being careless.",
    "status": "ready",
    "issues": "",
    "notes": "curated_batch24"
  },
  {
    "sourceText": "amuse",
    "text": "amuse",
    "level": "1",
    "translation": "楽しませる",
    "exampleJa": "",
    "exampleEn": "The magician amused the children.",
    "status": "ready",
    "issues": "",
    "notes": "curated_batch24"
  },
  {
    "sourceText": "overhaul",
    "text": "overhaul",
    "level": "1",
    "translation": "徹底的に見直す / 分解修理する",
    "exampleJa": "",
    "exampleEn": "The company plans to overhaul its website.",
    "status": "ready",
    "issues": "",
    "notes": "curated_batch24"
  },
  {
    "sourceText": "herd",
    "text": "herd",
    "level": "1",
    "translation": "群れ / 追い立てる",
    "exampleJa": "",
    "exampleEn": "A herd of deer crossed the field at dawn.",
    "status": "ready",
    "issues": "",
    "notes": "curated_batch24"
  },
  {
    "sourceText": "bait",
    "text": "bait",
    "level": "1",
    "translation": "えさ / おびき寄せるもの",
    "exampleJa": "",
    "exampleEn": "The fisherman put fresh bait on the hook.",
    "status": "ready",
    "issues": "",
    "notes": "curated_batch24"
  },
  {
    "sourceText": "petition",
    "text": "petition",
    "level": "1",
    "translation": "請願書 / 請願する",
    "exampleJa": "",
    "exampleEn": "Residents signed a petition against the plan.",
    "status": "ready",
    "issues": "",
    "notes": "curated_batch24"
  },
  {
    "sourceText": "ransom",
    "text": "ransom",
    "level": "1",
    "translation": "身代金",
    "exampleJa": "",
    "exampleEn": "The kidnappers demanded a ransom.",
    "status": "ready",
    "issues": "",
    "notes": "curated_batch24"
  },
  {
    "sourceText": "fragrance",
    "text": "fragrance",
    "level": "1",
    "translation": "香り",
    "exampleJa": "",
    "exampleEn": "The fragrance of fresh flowers filled the room.",
    "status": "ready",
    "issues": "",
    "notes": "curated_batch24"
  },
  {
    "sourceText": "conquest",
    "text": "conquest",
    "level": "1",
    "translation": "征服",
    "exampleJa": "",
    "exampleEn": "The museum exhibits tools from the age of conquest.",
    "status": "ready",
    "issues": "",
    "notes": "curated_batch24"
  },
  {
    "sourceText": "sincerity",
    "text": "sincerity",
    "level": "1",
    "translation": "誠実さ",
    "exampleJa": "",
    "exampleEn": "Her sincerity won the trust of the team.",
    "status": "ready",
    "issues": "",
    "notes": "curated_batch24"
  },
  {
    "sourceText": "tariff",
    "text": "tariff",
    "level": "1",
    "translation": "関税",
    "exampleJa": "",
    "exampleEn": "The new tariff raised import costs.",
    "status": "ready",
    "issues": "",
    "notes": "curated_batch24"
  },
  {
    "sourceText": "sanction",
    "text": "sanction",
    "level": "1",
    "translation": "制裁 / 認可",
    "exampleJa": "",
    "exampleEn": "The country faced economic sanctions.",
    "status": "ready",
    "issues": "",
    "notes": "curated_batch24"
  },
  {
    "sourceText": "outcast",
    "text": "outcast",
    "level": "1",
    "translation": "のけ者",
    "exampleJa": "",
    "exampleEn": "He felt like an outcast at the new school.",
    "status": "ready",
    "issues": "",
    "notes": "curated_batch24"
  },
  {
    "sourceText": "destruction",
    "text": "destruction",
    "level": "1",
    "translation": "破壊",
    "exampleJa": "",
    "exampleEn": "The earthquake caused widespread destruction.",
    "status": "ready",
    "issues": "",
    "notes": "curated_batch24"
  },
  {
    "sourceText": "peasant",
    "text": "peasant",
    "level": "1",
    "translation": "農民",
    "exampleJa": "",
    "exampleEn": "The book describes the lives of medieval peasants.",
    "status": "ready",
    "issues": "",
    "notes": "curated_batch24"
  },
  {
    "sourceText": "faculty",
    "text": "faculty",
    "level": "1",
    "translation": "学部 / 能力 / 教員団",
    "exampleJa": "",
    "exampleEn": "She joined the science faculty last year.",
    "status": "ready",
    "issues": "",
    "notes": "curated_batch24"
  },
  {
    "sourceText": "tactics",
    "text": "tactics",
    "level": "1",
    "translation": "戦術",
    "exampleJa": "",
    "exampleEn": "The coach changed the team's tactics at halftime.",
    "status": "ready",
    "issues": "",
    "notes": "curated_batch24"
  },
  {
    "sourceText": "correlation",
    "text": "correlation",
    "level": "1",
    "translation": "相関関係",
    "exampleJa": "",
    "exampleEn": "Researchers found a correlation between sleep and mood.",
    "status": "ready",
    "issues": "",
    "notes": "curated_batch24"
  },
  {
    "sourceText": "availability",
    "text": "availability",
    "level": "1",
    "translation": "利用可能性 / 入手可能性",
    "exampleJa": "",
    "exampleEn": "The availability of fresh water is a major concern.",
    "status": "ready",
    "issues": "",
    "notes": "curated_batch24"
  },
  {
    "sourceText": "prevention",
    "text": "prevention",
    "level": "1",
    "translation": "予防 / 防止",
    "exampleJa": "",
    "exampleEn": "Prevention is better than treatment in many cases.",
    "status": "ready",
    "issues": "",
    "notes": "curated_batch24"
  }
]
